[{"allUsersTargetingConfig":{"allocations":[{"percentage":10000,"weights":{"control":1,"treatment":1}}],"bucketingKey":"device_id","conditions":[],"name":"default-segment"},"bucketingKey":"device_id","bucketingSalt":"DdqDXcww","customSegmentTargetingConfigs":[{"allocations":[{"percentage":0,"weights":{"control":1,"treatment":1}}],"bucketingKey":"device_id","conditions":[{"op":"IS","prop":"gp:premium","values":["true"]}],"name":"Segment 1"}],"defaultValue":"off","enabled":true,"evalMode":"LOCAL","flagKey":"local-evaluation-demo","flagName":"local-evaluation-demo","flagVersion":4,"globalHoldbackBucketingKey":"amplitude_id","globalHoldbackPct":0,"globalHoldbackSalt":null,"mutualExclusionConfig":null,"type":"EXPERIMENT","useStickyBucketing":false,"userProperty":"[Experiment] local-evaluation-demo","variants":[{"key":"control","payload":null},{"key":"treatment","payload":null}],"variantsExclusions":null,"variantsInclusions":{}}]
